{
  "events": [
    {
      "id": "e_mo99cqqt4ms5j",
      "type": "vorfall",
      "title": "Betreuung Januar",
      "date": "2026-01-01",
      "segments": [
        11
      ],
      "hours": 56,
      "repeat": "none",
      "note": "",
      "subtype": null,
      "mode": null,
      "kanaele": null,
      "mechanikDauer": null,
      "dateEnd": "2026-01-31",
      "multiday": true
    },
    {
      "id": "e_mo99e0nzts1nj",
      "type": "vorfall",
      "title": "ZfP Betreuung Januar",
      "date": "2026-01-01",
      "segments": [
        12
      ],
      "hours": 36,
      "repeat": "none",
      "note": "",
      "subtype": null,
      "mode": null,
      "kanaele": null,
      "mechanikDauer": null,
      "dateEnd": "2026-01-31",
      "multiday": true
    }
  ],
  "vacations": [],
  "_meta": {
    "lastModified": "2026-04-21T23:32:33.868Z",
    "source": "jahresplan-app"
  }
}